xbootstrap/__init__.py
xbootstrap/_version.py
xbootstrap/core.py
xbootstrap/tests/test_core.py
xbootstrap-0.0.6.dist-info/LICENSE
xbootstrap-0.0.6.dist-info/METADATA
xbootstrap-0.0.6.dist-info/WHEEL
xbootstrap-0.0.6.dist-info/top_level.txt
xbootstrap-0.0.6.dist-info/RECORD
