Metadata-Version: 2.1
Name: xbootstrap
Version: 0.0.6
Summary: Nested circular block bootstrap resampling for xarray objects
Author: Dougie Squire
License: MIT
Classifier: Development Status :: 4 - Beta
Classifier: Programming Language :: Python :: 3
Classifier: License :: OSI Approved :: MIT License
Classifier: Operating System :: OS Independent
Requires-Python: >=3.9
License-File: LICENSE
Requires-Dist: numpy
Requires-Dist: xarray
